remQte/__init__.py
remQte/remQte.py
remQte/docs/img/icon.ico
remQte/docs/img/icon.png
remQte/docs/img/screenshot.png
remQte/qtui/importcsv_s1.ui
remQte/qtui/importcsv_s2.ui
remQte/qtui/importcsv_s3.ui
remQte/qtui/main_scan_choose_nets.ui
remQte/qtui/main_scan_nets.ui
remQte/qtui/main_start.ui
remQte/qtui/remote.ui
remQte/resources/__init__.py
remQte/resources/images.py
remQte/resources/importzip.py
remQte/resources/icon/icon16x16.png
remQte/resources/icon/icon24x24.png
remQte/resources/icon/icon256x256.png
remQte/resources/icon/icon32x32.png
remQte/resources/icon/icon48x48.png
remqte-0.2.1.dist-info/METADATA
remqte-0.2.1.dist-info/WHEEL
remqte-0.2.1.dist-info/entry_points.txt
remqte-0.2.1.dist-info/licenses/LICENSE
remqte-0.2.1.dist-info/RECORD
