Metadata-Version: 2.1
Name: remQte
Version: 0.2.1
Summary: Remote-control GUI for Samsung Smart TVs, newer than 2016.
Project-URL: Homepage, https://github.com/barfnordsen/remQte
Project-URL: Bug Tracker, https://github.com/barfnordsen/remQte/issues
Author-email: "Philipp M. Nöhren" <remQte@proton.me>
License-File: LICENSE
Classifier: Intended Audience :: End Users/Desktop
Classifier: License :: OSI Approved :: MIT License
Classifier: Programming Language :: Python :: 3.9
Classifier: Programming Language :: Python :: 3.10
Classifier: Programming Language :: Python :: 3.11
Requires-Python: >=3.9
Requires-Dist: netifaces
Requires-Dist: pyqt6
Requires-Dist: samsungtvws
Requires-Dist: ssdpy
Requires-Dist: wakeonlan
